{"auras":[{"name":"Emma Neotoma","id":19,"guid":1000018,"type":"RedMage","icon":"RedMage","totalUptime":713547,"totalUses":53,"bands":[{"startTime":46695897,"endTime":46783468},{"startTime":47236316,"endTime":47266315},{"startTime":47289489,"endTime":47331985},{"startTime":47351006,"endTime":47395249},{"startTime":47801677,"endTime":47885976},{"startTime":47920420,"endTime":48005518},{"startTime":48029527,"endTime":48063024},{"startTime":48246278,"endTime":48269847},{"startTime":48308250,"endTime":48458971},{"startTime":48903974,"endTime":48980118},{"startTime":49062898,"endTime":49111809},{"startTime":49136006,"endTime":49143005}]}],"useTargets":false,"totalTime":2698695,"startTime":45961493,"endTime":51622192}
